spacez/__init__.py
spacez/blur.py
spacez/spacez_2d.py
spacez-0.1.0.dist-info/AUTHORS.rst
spacez-0.1.0.dist-info/LICENSE
spacez-0.1.0.dist-info/METADATA
spacez-0.1.0.dist-info/WHEEL
spacez-0.1.0.dist-info/top_level.txt
spacez-0.1.0.dist-info/RECORD
