Metadata-Version: 2.1
Name: spacez
Version: 0.1.0
Summary: Spatial K-means clustering
Author-email: Petrus Zwart <phzwart@lbl.gov>
Maintainer-email: Petrus Zwart <phzwart@lbl.gov>
License: BSD license
Project-URL: bugs, https://github.com/phzwart/spacez/issues
Project-URL: changelog, https://github.com/phzwart/spacez/blob/master/changelog.md
Project-URL: homepage, https://github.com/phzwart/spacez
License-File: LICENSE
License-File: AUTHORS.rst
Provides-Extra: dev
Requires-Dist: coverage ; extra == 'dev'
Requires-Dist: mypy ; extra == 'dev'
Requires-Dist: pytest ; extra == 'dev'
Requires-Dist: ruff ; extra == 'dev'
